slide/__init__.py
slide/_slide.py
slide/_analysis/__init__.py
slide/_analysis/_base.py
slide/_analysis/_loader.py
slide/_analysis/_window.py
slide/_analysis/_stats/__init__.py
slide/_analysis/_stats/_base.py
slide/_analysis/_stats/_tests.py
slide/_analysis/_stats/_types.py
slide/_annotation/__init__.py
slide/_annotation/_base.py
slide/_annotation/_io.py
slide/_input/__init__.py
slide/_input/_base.py
slide/_input/_io.py
slide/_input/_formats/__init__.py
slide/_input/_formats/_load_array.py
slide/_input/_formats/_load_csv.py
slide/_input/_formats/_load_cytoscape.py
slide/_input/_formats/_load_dataframe.py
slide/_input/_formats/_load_dict.py
slide/_input/_formats/_load_excel.py
slide/_input/_formats/_load_gpickle.py
slide/_input/_formats/_load_json.py
slide/_input/_formats/_load_networkx.py
slide/_input/_formats/_load_tsv.py
slide/_input/_formats/_loader.py
slide/_input/_formats/_log_loading.py
slide/_log/__init__.py
slide/_log/_console.py
slide/_log/_parameters.py
slide/_plot/__init__.py
slide/_plot/_base.py
slide/_plot/_canvas.py
slide/_plot/_heatbar.py
slide/_plot/_line.py
slide/_plot/_pulsar.py
slide/_results/__init__.py
slide/_results/_base.py
slide/_results/_cluster.py
slidekit-0.0.3.dist-info/licenses/LICENSE
slidekit-0.0.3.dist-info/METADATA
slidekit-0.0.3.dist-info/WHEEL
slidekit-0.0.3.dist-info/top_level.txt
slidekit-0.0.3.dist-info/RECORD
